{
  "$schema": "https://json-schema.org/draft/2020-12/schema",
  "$id": "https://pfr.local/schemas/third_party_audit/diagnosis/prevalence_summary_v0_1.json",
  "title": "Third-party audit prevalence summary v0.1",
  "type": "object",
  "additionalProperties": true,
  "required": ["schema_version", "schema_path", "run_id", "method", "prevalence_views", "claim_boundary"],
  "properties": {
    "schema_version": {"type": "string", "const": "prevalence_summary_v0_1"},
    "schema_path": {"type": "string", "const": "schemas/third_party_audit/diagnosis/prevalence_summary_v0_1.json"},
    "run_id": {"type": "string"},
    "method": {"type": "string"},
    "prevalence_views": {"type": "object", "additionalProperties": true},
    "claim_boundary": {"type": "string"}
  }
}
